[
  {
    "title": "Top Premier League highlights from Matchweek 38 (2023-24)",
    "link": "https://www.youtube.com/watch?v=le69J9tVVcQ",
    "snippet": "https://www.youtube.com/nbcsports?sub_confirmation=1 » Watch Live Sports on NBC.com ...",
    "date": "May 21, 2024",
    "attributes": { "Duration": "26:22", "Posted": "May 21, 2024" },
    "imageUrl": "https://i.ytimg.com/vi/le69J9tVVcQ/default.jpg?sqp=-oaymwEECHgQQw&rs=AMzJL3mds9eUZECCVqZbHnvVznWuznegow",
    "position": 7,
    "searched": 1722800929.0494359
  },
  {
    "title": "Brighton v. Manchester United Matchweek 38 | 5/19/2024 | NBC Sports",
    "link": "https://www.youtube.com/watch?v=_Z8cHDO8oEg",
    "snippet": "... PremierLeague #ManchesterCity #WestHam » Subscribe to NBC Sports: https://www.youtube ...",
    "date": "May 19, 2024",
    "attributes": { "Duration": "15:20", "Posted": "May 19, 2024" },
    "imageUrl": "https://i.ytimg.com/vi/_Z8cHDO8oEg/default.jpg?sqp=-oaymwEECHgQQw&rs=AMzJL3nN4mJ-Xr6LdngHtRh58SLrBa6R9w",
    "position": 9,
    "searched": 1722800929.049744
  },
  {
    "title": "145th Last Season | Fantasy Premier League 2024/25 - YouTube",
    "link": "https://www.youtube.com/watch?v=5MsMjM_Wa48",
    "snippet": "Former Premier League footballer who finished 145th in FPL last season, Matt Heath shows ...",
    "date": "7 days ago",
    "attributes": { "Duration": "39:54", "Posted": "7 days ago" },
    "imageUrl": "https://i.ytimg.com/vi/5MsMjM_Wa48/default.jpg?sqp=-oaymwEECHgQQw&rs=AMzJL3nHddUmkGXf_cpByeFDYGcWqHe2zw",
    "position": 6,
    "searched": 1722800932.120905
  },
  {
    "title": "FPL PRE-SEASON FORM PLAYERS - YouTube",
    "link": "https://www.youtube.com/watch?v=PWo2gEjH348",
    "snippet": "... videos: https://youtu.be/Sf2u_FOodAU ... | FPL Fantasy Premier League 24/25 Strategy and ...",
    "date": "1 day ago",
    "attributes": { "Duration": "14:46", "Posted": "1 day ago" },
    "imageUrl": "https://i.ytimg.com/vi/PWo2gEjH348/default.jpg?sqp=-oaymwEECHgQQw&rs=AMzJL3nE-ssO818QaDL35lU43uFe5lmLPg",
    "position": 7,
    "searched": 1722800932.121021
  },
  {
    "title": "Premier League Players With MOST ASSISTS | 2023/24 Edition",
    "link": "https://www.youtube.com/watch?v=qZhIZk-5apY",
    "snippet": "... Premier League YouTube channel: http://preml.ge/PremierLeagueYouTube Premier League ...",
    "date": "Jul 3, 2024",
    "attributes": { "Duration": "10:42", "Posted": "Jul 3, 2024" },
    "imageUrl": "https://encrypted-tbn3.gstatic.com/images?q=tbn:ANd9GcRQ2U_u_cjA_3iu7ZwrZiOV2qMTGG4YaML2C5Brsl65k-sCOKDwAxf-stiw",
    "position": 8,
    "searched": 1722800932.12113
  },
  {
    "title": "Ranking the 10 BEST players in the Premier League this season",
    "link": "https://www.youtube.com/watch?v=voLhDre99yU",
    "snippet": "... football MORE FROM SKY SPORTS ON YOUTUBE: ▻SKY SPORTS PREMIER LEAGUE ...",
    "date": "May 19, 2024",
    "attributes": { "Duration": "20:46", "Posted": "May 19, 2024" },
    "imageUrl": "https://i.ytimg.com/vi/voLhDre99yU/default.jpg?sqp=-oaymwEECHgQQw&rs=AMzJL3ltwFz6H1czDWu3qrkiWXGq2m1OZQ",
    "position": 9,
    "searched": 1722800932.1213288
  },
  {
    "title": "Fantasy Premier League Tips 2024/25 - YouTube",
    "link": "https://www.youtube.com/watch?v=v_kf6r5BfPo",
    "snippet": "... video I talk through some of current FPL first drafts ahead of the Fantasy Premier League ...",
    "date": "11 hours ago",
    "attributes": { "Duration": "33:44", "Posted": "11 hours ago" },
    "imageUrl": "https://i.ytimg.com/vi/v_kf6r5BfPo/default.jpg?sqp=-oaymwEECHgQQw&rs=AMzJL3mxXOf78OKSTssPl-R8dWSr3BeaHQ",
    "position": 10,
    "searched": 1722800932.12144
  },
  {
    "title": "Fantasy Premier League Tips 2024/25 - YouTube",
    "link": "https://www.youtube.com/watch?v=v_kf6r5BfPo",
    "snippet": "... video I talk through some of current FPL first drafts ahead of ... REVIEWING YOUR CURRENT ...",
    "date": "11 hours ago",
    "attributes": { "Duration": "33:44", "Posted": "11 hours ago" },
    "imageUrl": "https://i.ytimg.com/vi/v_kf6r5BfPo/default.jpg?sqp=-oaymwEECHgQQw&rs=AMzJL3mxXOf78OKSTssPl-R8dWSr3BeaHQ",
    "position": 4,
    "searched": 1722800934.987423
  },
  {
    "title": "8 x TOP 10K! | Fantasy Premier League Tips 2024/25 - YouTube",
    "link": "https://www.youtube.com/watch?v=hpnfFxsq0lI",
    "snippet": "Joe reveals his latest FPL DRAFTS! Mo Salah or No Salah?! Team Selection ...",
    "date": "13 hours ago",
    "attributes": { "Duration": "24:54", "Posted": "13 hours ago" },
    "imageUrl": "https://i.ytimg.com/vi/hpnfFxsq0lI/default.jpg?sqp=-oaymwEECHgQQw&rs=AMzJL3mTqqHNxqY6Tujcei-zdwdP3KSNtw",
    "position": 6,
    "searched": 1722800934.987681
  },
  {
    "title": "FPL TEAMS from FIVE Champions! - YouTube",
    "link": "https://www.youtube.com/watch?v=gp77bDewdEQ",
    "snippet": "... we'll do your team. 33:44 · Go to channel. REVIEWING YOUR CURRENT FPL TEAMS ...",
    "date": "4 days ago",
    "attributes": { "Duration": "12:45", "Posted": "4 days ago" },
    "imageUrl": "https://i.ytimg.com/vi/gp77bDewdEQ/default.jpg?sqp=-oaymwEECHgQQw&rs=AMzJL3lcIXzI_c9tuD6J1DaRT9rj3eeiiQ",
    "position": 8,
    "searched": 1722800934.987946
  },
  {
    "title": "MY LATEST FPL DRAFT FOR GAMEWEEK 1 - YouTube",
    "link": "https://www.youtube.com/watch?v=3zU_VLYdgQI",
    "snippet": "... YouTube fpl gurus. 33:44 · Go to channel. REVIEWING YOUR CURRENT FPL TEAMS ...",
    "date": "3 days ago",
    "attributes": { "Duration": "19:52", "Posted": "3 days ago" },
    "imageUrl": "https://i.ytimg.com/vi/3zU_VLYdgQI/default.jpg?sqp=-oaymwEECHgQQw&rs=AMzJL3k2GbnuywzgogAdT2Cmu4h24j52lg",
    "position": 9,
    "searched": 1722800934.988137
  },
  {
    "title": "The CRAZIEST FPL Team - YouTube",
    "link": "https://www.youtube.com/watch?v=MhpcZOhuP1k",
    "snippet": "I asked for your most creative FPL teams for Fantasy Premier League 2024/25! Join FFScout ...",
    "date": "2 days ago",
    "attributes": { "Duration": "9:06", "Posted": "2 days ago" },
    "imageUrl": "https://i.ytimg.com/vi/MhpcZOhuP1k/default.jpg?sqp=-oaymwEECHgQQw&rs=AMzJL3nS0Oij9kxaFwcqLQV1kPVJIz8ZwQ",
    "position": 10,
    "searched": 1722800934.988275
  },
  {
    "title": "Top Plays of The 2023 Regular Season | NFL Highlights - YouTube",
    "link": "https://www.youtube.com/watch?v=WugoszGta-w",
    "snippet": "... youtube.com/nflnetwork #NFL #Football #AmericanFootball. ... Football H9Studio New 66K ...",
    "date": "Jan 8, 2024",
    "attributes": { "Duration": "49:27", "Posted": "Jan 8, 2024" },
    "imageUrl": "https://i.ytimg.com/vi/WugoszGta-w/default.jpg?sqp=-oaymwEECHgQQw&rs=AMzJL3keF3m8wvKxgKwRYoM9v-1MX-tuNA",
    "position": 3,
    "searched": 1722800938.36733
  },
  {
    "title": "Top 100 Plays of the 2023 Season! - YouTube",
    "link": "https://www.youtube.com/watch?v=tJFHlzw8vVE",
    "snippet": "... youtube.com/nflnetwork #NFL #Football #AmericanFootball. ... Highlight Reel•3.4M views ...",
    "date": "Feb 12, 2024",
    "attributes": { "Duration": "27:13", "Posted": "Feb 12, 2024" },
    "imageUrl": "https://i.ytimg.com/vi/tJFHlzw8vVE/default.jpg?sqp=-oaymwEECHgQQw&rs=AMzJL3kEahKencbpNEgdpwZiqE7kpt4RdA",
    "position": 6,
    "searched": 1722800938.3676631
  },
  {
    "title": "Every Team's Longest Play from the 2023 Regular Season - YouTube",
    "link": "https://www.youtube.com/watch?v=OkVbauRlDEc",
    "snippet": "Puka literally had an 80 yard catch in the giants game. Come on NFL. 30:24 · Go to channel ...",
    "date": "Jan 9, 2024",
    "attributes": { "Duration": "10:52", "Posted": "Jan 9, 2024" },
    "imageUrl": "https://i.ytimg.com/vi/OkVbauRlDEc/default.jpg?sqp=-oaymwEECHgQQw&rs=AMzJL3mEHjS0URvhDVe-EOdNdAy61imZTg",
    "position": 9,
    "searched": 1722800938.368245
  },
  {
    "title": "NFL Speed Kills Moments of the 2023-2024 Season - YouTube",
    "link": "https://www.youtube.com/watch?v=TTZTJ3qrYgQ",
    "snippet": "Comments137. Goat. Weird way of saying dolphins highlight reel ... Top Plays of The 2023 ...",
    "date": "Apr 11, 2024",
    "attributes": { "Duration": "28:24", "Posted": "Apr 11, 2024" },
    "imageUrl": "https://i.ytimg.com/vi/TTZTJ3qrYgQ/default.jpg?sqp=-oaymwEECHgQQw&rs=AMzJL3lkY04Y5D0yM7xaE8WVWx9F3_UicA",
    "position": 10,
    "searched": 1722800938.3684359
  },
  {
    "title": "BREAKING NEWS! Miami Dolphins Give Tyreek Hill Most ... - YouTube",
    "link": "https://www.youtube.com/watch?v=eqFqpQiGa7Q",
    "snippet": "Tyreek Hill was also named the #1 NFL Player by his peers on the NFL's Top 100 ...",
    "date": "24 hours ago",
    "attributes": { "Duration": "1:00:35", "Posted": "24 hours ago" },
    "imageUrl": "https://i.ytimg.com/vi/eqFqpQiGa7Q/default.jpg?sqp=-oaymwEECHgQQw&rs=AMzJL3kbmo6q6hAvryfZu54fNEr-nh4YiA",
    "position": 3,
    "searched": 1722800941.6437628
  },
  {
    "title": "NFL Players Snubbed From Top 100 Players List - YouTube",
    "link": "https://www.youtube.com/watch?v=Mx8ndidqPXc",
    "snippet": "Share your videos with friends, family, and the world.",
    "date": "23 hours ago",
    "attributes": { "Duration": "1:33", "Posted": "23 hours ago" },
    "imageUrl": "https://i.ytimg.com/vi/Mx8ndidqPXc/default.jpg?sqp=-oaymwEECHgQQw&rs=AMzJL3nj7BnNMZMbyqV1-TiL19s7MOIgyQ",
    "position": 5,
    "searched": 1722800941.644108
  },
  {
    "title": "Fantasy Football Predictions For 284 NFL Players - YouTube",
    "link": "https://www.youtube.com/watch?v=KmWvkLdb2u4",
    "snippet": "43:38 · Go to channel · 5 Players Brett Kollmann Can't Stop Drafting - Fantasy Football ...",
    "date": "4 days ago",
    "attributes": { "Duration": "1:53:28", "Posted": "4 days ago" },
    "imageUrl": "https://i.ytimg.com/vi/KmWvkLdb2u4/default.jpg?sqp=-oaymwEECHgQQw&rs=AMzJL3mNTTWstQWWpZY7SSLxz0_dL9TD8w",
    "position": 8,
    "searched": 1722800941.644755
  },
  {
    "title": "Top Plays of The 2023 Regular Season | NFL Highlights - YouTube",
    "link": "https://www.youtube.com/watch?v=WugoszGta-w",
    "snippet": "... youtube.com/nflnetwork #NFL #Football #AmericanFootball. ... Football H9Studio New 66K ...",
    "date": "Jan 8, 2024",
    "attributes": { "Duration": "49:27", "Posted": "Jan 8, 2024" },
    "imageUrl": "https://i.ytimg.com/vi/WugoszGta-w/default.jpg?sqp=-oaymwEECHgQQw&rs=AMzJL3keF3m8wvKxgKwRYoM9v-1MX-tuNA",
    "position": 9,
    "searched": 1722800941.645217
  },
  {
    "title": "My Thoughts on The New NFL Kickoff - YouTube",
    "link": "https://www.youtube.com/watch?v=w5ntrmraTGc",
    "snippet": "TK Twelve 2024 NFL Football Videos #nfl #football # ... FUNNIEST Undercover NFL Player ...",
    "date": "2 hours ago",
    "attributes": { "Duration": "1:41", "Posted": "2 hours ago" },
    "imageUrl": "https://i.ytimg.com/vi/w5ntrmraTGc/default.jpg?sqp=-oaymwEECHgQQw&rs=AMzJL3l1uKSd4iQglgNhVwSp7s6sC6JIrQ",
    "position": 10,
    "searched": 1722800941.645403
  },
  {
    "title": "The Pittsburgh Steelers Have One Problem | 2024 NFL ... - YouTube",
    "link": "https://www.youtube.com/watch?v=3UyD68DnxiQ",
    "snippet": "... teams. 40:10 · Go to channel. The Green Bay Packers Are Dangerous | 2024 NFL Team ...",
    "date": "1 day ago",
    "attributes": { "Duration": "19:48", "Posted": "1 day ago" },
    "imageUrl": "https://i.ytimg.com/vi/3UyD68DnxiQ/default.jpg?sqp=-oaymwEECHgQQw&rs=AMzJL3nxzOQXx-QgtyhYXqG_sqVy-AYr1A",
    "position": 5,
    "searched": 1722800944.612273
  },
  {
    "title": "The Green Bay Packers Are Dangerous | 2024 NFL Team Previews ...",
    "link": "https://www.youtube.com/watch?v=DT-F08GDV_A",
    "snippet": "Subscribe for all NFL related content! Drop a like if you enjoyed the video ... Football Analysis ...",
    "date": "3 days ago",
    "attributes": { "Duration": "40:10", "Posted": "3 days ago" },
    "imageUrl": "https://i.ytimg.com/vi/DT-F08GDV_A/default.jpg?sqp=-oaymwEECHgQQw&rs=AMzJL3lRu7tVInRei_4J5EDMFZ53lSvCgA",
    "position": 7,
    "searched": 1722800944.612546
  }
]
